* ##### 使用Object 需要强转

```java
public class Holder2 {
    private Object a;

    public Holder2(Object a) {
        this.a = a;
    }

    public void set(Object a) {
        this.a = a;
    }

    public Object get() {
        return a;
    }

    public static void main(String[] args) {
        Holder2 h2 = new Holder2(new Automobile());
        Automobile a = (Automobile) h2.get();
        h2.set("Not an Automobile");
        String s = (String) h2.get();
        h2.set(1); // Autoboxes to Integer
        Integer x = (Integer) h2.get();
    }
} ///:~
```

* ##### 使用泛型 不需要强转

```java
public class Holder3<T> {
    private T a;

    public Holder3(T a) {
        this.a = a;
    }

    public void set(T a) {
        this.a = a;
    }

    public T get() {
        return a;
    }

    public static void main(String[] args) {
        Holder3<Automobile> h3 = new Holder3<Automobile>(new Automobile());
        Automobile a = h3.get(); // No cast needed
        // h3.set("Not an Automobile"); // Error
        // h3.set(1); // Error
    }
} ///:~
```

##### 15.4  泛型方法

  泛型方法使得改方法能够独立于类而产生变化。以下是一个基本的指导原则：

​	无论何时，只要你能做到，你就应该尽量使用泛型方法。也就是说，如果**使用泛型方法**可以取代**将整个类泛型化**，**那么就应该只使用泛型方法**，因为它可以使事情更清楚明白。另外，对于一个static的方法而言，**无法访问泛型类的类型参数**，所以，如果static方法需要使用泛型能力，**就必须使其成为泛型方法**。

```java
public class GenericMethods {
    public <T> void f(T x) {
        System.out.println(x.getClass().getName());
    }

    public static void main(String[] args) {
        GenericMethods gm = new GenericMethods();
        gm.f("");
        gm.f(1);
        gm.f(1.0);
        gm.f(1.0F);
        gm.f('c');
        gm.f(gm);
    }
} /* Output:
java.lang.String
java.lang.Integer
java.lang.Double
java.lang.Float
java.lang.Character
GenericMethods
*///:~
```

##### 15.4.1 杠杆利用类型参数推断

```java
public static <K, V> Map<K, V> map() {
    return new HashMap<K, V>();
}
```

```java
public class LimitsOfInference {
    static void f(Map<Person, List<? extends Pet>> petPeople) { }

    public static void main(String[] args) {
        // f(New.map()); // Does not compile
    }
} ///:~
```

```java
public class ExplicitTypeSpecification {
    static void f(Map<Person, List<Pet>> petPeople) {
    }

    public static void main(String[] args) {
        f(New.<Person, List<Pet>>map());
    }
} ///:~
```

##### 15.4.2 可变参数与泛型方法

```java
public class GenericVarargs {
    public static <T> List<T> makeList(T... args) {
        List<T> result = new ArrayList<T>();
        for (T item : args) {
            result.add(item);
        }
        return result;
    }

    public static void main(String[] args) {
        List<String> ls = makeList("A");
        System.out.println(ls);
        ls = makeList("A", "B", "C");
        System.out.println(ls);
        ls = makeList("ABCDEFFHIJKLMNOPQRSTUVWXYZ".split(""));
        System.out.println(ls);
    }
} /* Output:
[A]
[A, B, C]
[, A, B, C, D, E, F, F, H, I, J, K, L, M, N, O, P, Q, R, S, T, U, V, W, X, Y, Z]
*///:~
```

##### 15.4.3 用于Generator的泛型方法

##### 15.4.4 一个通用的Generator

```java
public interface Generator<T> {
    T next();
} ///:~
```

```java
public class BasicGenerator<T> implements Generator<T> {
    private Class<T> type;

    public BasicGenerator(Class<T> type) {
        this.type = type;
    }

    public T next() {
        try {
            // Assumes type is a public class:
            return type.newInstance();
        } catch (Exception e) {
            throw new RuntimeException(e);
        }
    }

    // Produce a Default generator given a type token:
    public static <T> Generator<T> create(Class<T> type) {
        return new BasicGenerator<T>(type);
    }
} ///:~
```

这个类必须具备两个特点：

* 它必须声明为public。(应为BasicGenerator与要处理的类在不同的包中，所以该类必须声明为public，并且不只具有包内访问权限)。
* 它必须具备默认的构造器(无参构造器)。要创建这样的BasicGenerator对象，只需调用create()方法，并传入想要生成的类型。防滑的create()方法允许执行BasicGenerator.create(MyType.class)，而不必执行麻烦的 new BasicGenerator<MyType>(Mytype.class)

下面示例：

```java
public class CountedObject {
    private static long counter = 0;
    private final long id = counter++;

    public long id() {
        return id;
    }

    public String toString() {
        return "CountedObject " + id;
    }
} ///:~
```

```java
public class BasicGeneratorDemo {
    public static void main(String[] args) {
        Generator<CountedObject> gen = BasicGenerator.create(CountedObject.class);
        for (int i = 0; i < 5; i++) {
            System.out.println(gen.next());
        }
    }
} /* Output:
CountedObject 0
CountedObject 1
CountedObject 2
CountedObject 3
CountedObject 4
*///:~
```

##### 15.4.5 简化元组的使用

##### 15.4.6 一个Set使用工具

##### 15.5 匿名内部类

##### 15.7 擦除的神秘之处

```java
public class ErasedTypeEquivalence {
    public static void main(String[] args) {
        Class c1 = new ArrayList<String>().getClass();
        Class c2 = new ArrayList<Integer>().getClass();
        System.out.println(c1 == c2);
    }
} /* Output:
true
*///:~
```

```java
class Frob {
}

class Fnorkle {
}

class Quark<Q> {
}

class Particle<POSITION, MOMENTUM> {
}

public class LostInformation {
    public static void main(String[] args) {
        List<Frob> list = new ArrayList<Frob>();
        Map<Frob, Fnorkle> map = new HashMap<Frob, Fnorkle>();
        Quark<Fnorkle> quark = new Quark<Fnorkle>();
        Particle<Long, Double> p = new Particle<Long, Double>();
        System.out.println(Arrays.toString(
                list.getClass().getTypeParameters()));
        System.out.println(Arrays.toString(
                map.getClass().getTypeParameters()));
        System.out.println(Arrays.toString(
                quark.getClass().getTypeParameters()));
        System.out.println(Arrays.toString(
                p.getClass().getTypeParameters()));
    }
} /* Output:
[E]
[K, V]
[Q]
[POSITION, MOMENTUM]
*///:~
```

**getClass().getTypeParameters()**返回泛型声明所声明的类型参数。

```java
public class GenericHolder<T> {
    private T obj;

    public void set(T obj) {
        this.obj = obj;
    }

    public T get() {
        return obj;
    }

    public static void main(String[] args) {
        GenericHolder<String> holder = new GenericHolder<String>();
        holder.set("Item");
        String s = holder.get();
    }
} ///:~
/*
public class com.zping.lib_thinking_in_java.t15_generics.SimpleHolder {
  public com.zping.lib_thinking_in_java.t15_generics.SimpleHolder();
    Code:
       0: aload_0
       1: invokespecial #1                  // Method java/lang/Object."<init>":()V
       4: return

  public void set(java.lang.Object);
    Code:
       0: aload_0
       1: aload_1
       2: putfield      #2                  // Field obj:Ljava/lang/Object;
       5: return

  public java.lang.Object get();
    Code:
       0: aload_0
       1: getfield      #2                  // Field obj:Ljava/lang/Object;
       4: areturn

  public static void main(java.lang.String[]);
    Code:
       0: new           #3                  // class com/zping/lib_thinking_in_java/t15_generics/SimpleHolder
       3: dup
       4: invokespecial #4                  // Method "<init>":()V
       7: astore_1
       8: aload_1
       9: ldc           #5                  // String Item
      11: invokevirtual #6                  // Method set:(Ljava/lang/Object;)V
      14: aload_1
      15: invokevirtual #7                  // Method get:()Ljava/lang/Object;
      18: checkcast     #8                  // class java/lang/String
      21: astore_2
      22: return
}

*/

```

对于set()的类型进行检查是不需要的，因为这将由编译器执行。

对于get()返回的值进行转换仍旧是需要的，但这与你自己必须执行的操作是一样的—此处它将由编译器自动插入。

##### 15.8 擦除的补偿

```java
public class Erased<T> {
    private final int SIZE = 100;

    public static void f(Object arg) {
//        if (arg instanceof T) {
//        }          // Error
//        T var = new T();                 // Error
//        T[] array = new T[SIZE];         // Error
//        T[] array = (T) new Object[SIZE]; // Unchecked warning
    }
} ///:~
```

```java
class Building {
}

class House extends Building {
}

public class ClassTypeCapture<T> {
    Class<T> kind;

    public ClassTypeCapture(Class<T> kind) {
        this.kind = kind;
    }

    public boolean f(Object arg) {
        return kind.isInstance(arg);
    }

    public static void main(String[] args) {
        ClassTypeCapture<Building> ctt1 =
                new ClassTypeCapture<Building>(Building.class);
        System.out.println(ctt1.f(new Building()));
        System.out.println(ctt1.f(new House()));
        ClassTypeCapture<House> ctt2 =
                new ClassTypeCapture<House>(House.class);
        System.out.println(ctt2.f(new Building()));
        System.out.println(ctt2.f(new House()));
    }
} /* Output:
true
true
false
true
*///:~
```

##### 15.8.2 泛型数组

```java
public class ArrayOfGenericType<T> {
  T[] array; // OK
  @SuppressWarnings("unchecked")
  public ArrayOfGenericType(int size) {
    //! array = new T[size]; // Illegal
    array = (T[])new Object[size]; // "unchecked" Warning
  }
  // Illegal:
  //! public <U> U[] makeArray() { return new U[10]; }
} ///:~
```

```java
public class GenericArrayWithTypeToken<T> {
    private T[] array;

    @SuppressWarnings("unchecked")
    public GenericArrayWithTypeToken(Class<T> type, int sz) {
        array = (T[]) Array.newInstance(type, sz);
    }

    public void put(int index, T item) {
        array[index] = item;
    }

    public T get(int index) {
        return array[index];
    }

    // Expose the underlying representation:
    public T[] rep() {
        return array;
    }

    public static void main(String[] args) {
        GenericArrayWithTypeToken<Integer> gai = new GenericArrayWithTypeToken<Integer>(
                        Integer.class, 10);
        // This now works:
        Integer[] ia = gai.rep();
    }
} ///:~
```

##### 15.9 边界







